pynevin/__init__.py
pynevin/cli.py
pynevin/hello.py
pynevin/pypi.py
pynevin/visualsim.py
pynevin/Crack/Chapter_1.py
pynevin/Crack/Chapter_2.py
pynevin/Crack/Chapter_3.py
pynevin/Crack/Chapter_4.py
pynevin/Crack/Chapter_5.py
pynevin/Crack/__init__.py
pynevin/Test/Car.py
pynevin/Test/Vehicle.py
pynevin/Test/__init__.py
pynevin-0.1.21.dist-info/LICENSE
pynevin-0.1.21.dist-info/METADATA
pynevin-0.1.21.dist-info/WHEEL
pynevin-0.1.21.dist-info/entry_points.txt
pynevin-0.1.21.dist-info/top_level.txt
pynevin-0.1.21.dist-info/RECORD
