Metadata-Version: 2.1
Name: pynevin
Version: 0.1.21
Summary: Nevin's Python Packages: Algorithms, Utils, Leetcode & Helper functions
Home-page: https://github.com/iDuckDark/PyNevin
Author: Nevin WS Ganesan
Author-email: PyNevin@idarkduck.com
License: Apache License 2.0
Platform: UNKNOWN
Requires-Dist: click
